tkrouter/__init__.py
tkrouter/create_app.py
tkrouter/exceptions.py
tkrouter/history.py
tkrouter/router.py
tkrouter/router_outlet.py
tkrouter/transitions.py
tkrouter/types.py
tkrouter/utils.py
tkrouter/views.py
tkrouter/widgets.py
tkrouter/__pycache__/__init__.cpython-313.pyc
tkrouter/__pycache__/create_app.cpython-313.pyc
tkrouter/__pycache__/exceptions.cpython-313.pyc
tkrouter/__pycache__/history.cpython-313.pyc
tkrouter/__pycache__/router.cpython-313.pyc
tkrouter/__pycache__/router_outlet.cpython-313.pyc
tkrouter/__pycache__/transitions.cpython-313.pyc
tkrouter/__pycache__/types.cpython-313.pyc
tkrouter/__pycache__/utils.cpython-313.pyc
tkrouter/__pycache__/views.cpython-313.pyc
tkrouter/__pycache__/widgets.cpython-313.pyc
tkrouter/examples/__init__.py
tkrouter/examples/admin_console.py
tkrouter/examples/guarded_routes.py
tkrouter/examples/minimal_app.py
tkrouter/examples/unified_routing.py
tkrouter-0.2.0.dist-info/licenses/LICENSE
tkrouter-0.2.0.dist-info/METADATA
tkrouter-0.2.0.dist-info/WHEEL
tkrouter-0.2.0.dist-info/entry_points.txt
tkrouter-0.2.0.dist-info/top_level.txt
tkrouter-0.2.0.dist-info/RECORD
