Metadata-Version: 2.4
Name: tkrouter
Version: 0.2.0
Summary: Declarative routing and animated navigation for Tkinter.
Author-email: Israel Dryer <israel.dryer@gmail.com>
License-Expression: MIT
Project-URL: Homepage, https://github.com/israel-dryer/tkrouter
Project-URL: Source, https://github.com/israel-dryer/tkrouter
Project-URL: Bug Tracker, https://github.com/israel-dryer/tkrouter/issues
Requires-Python: >=3.8
License-File: LICENSE
Dynamic: license-file
